{"Events": [{"station 4 health": 58, "secondsLeft": 58, "station 2 health": 58, "station 1 health": 58, "stationEvent": "show", "stationNumber": "Station1", "score": -2, "_id": 1, "station 3 health": 58}, {"station 4 health": 57, "secondsLeft": 57, "station 2 health": 57, "station 1 health": 57, "stationEvent": "hide", "stationNumber": "Station1", "score": -2, "_id": 2, "station 3 health": 57}, {"station 4 health": 56, "secondsLeft": 56, "station 2 health": 56, "station 1 health": 56, "stationEvent": "show", "stationNumber": "Station2", "score": -5, "_id": 3, "station 3 health": 56}, {"station 4 health": 55, "secondsLeft": 55, "station 2 health": 55, "station 1 health": 55, "stationEvent": "hide", "stationNumber": "Station2", "score": -5, "_id": 4, "station 3 health": 55}]}